{"is_source_file": true, "format": "JavaScript (React JSX)", "description": "This file defines the AppShell component, which provides the main layout for the application including a navbar with branding, search bar, user info, and sign-out functionality; and a main content area with search context wrapping.", "external_files": ["../auth/AuthContext", "../shared/SearchBar", "./SearchProviderWrapper"], "external_methods": ["useAuth"], "published": ["default"], "classes": [], "methods": [{"name": "AppShell({ children })", "description": "React functional component serving as the application shell layout, including navigation bar and main content area.", "scope": "", "scopeKind": ""}], "calls": ["useAuth", "signOut", "SearchBar", "SearchProviderWrapper"], "search-terms": ["AppShell", "React component", "navigation bar", "search", "authentication", "sign out", "layout"], "state": 2, "file_id": 14, "knowledge_revision": 50, "git_revision": "", "revision_history": [{"32": ""}, {"50": ""}], "ctags": [{"_type": "tag", "name": "AppShell", "path": "/home/kavia/workspace/code-generation/recipe-explorer-154988-154997/recipe_frontend/src/layout/AppShell.js", "pattern": "/^export default function AppShell({ children }) {$/", "language": "JavaScript", "kind": "function", "signature": "({ children })"}], "hash": "2c436c79aaa25b2b28d606209256651e", "format-version": 4, "code-base-name": "recipe_frontend", "filename": "recipe_frontend/src/layout/AppShell.js"}